canaveral/__init__.py
canaveral/basemodels.py
canaveral/main.py
canaveral/paths-example.py
canaveral/qtmodels.py
canaveral/resources.py
canaveral/resources_rc.py
canaveral/widgets.py
canaveral/qtkeybind/__init__.py
canaveral/qtkeybind/win/__init__.py
canaveral/qtkeybind/win/keybindutil.py
canaveral/qtkeybind/win/keycodes.py
canaveral/qtkeybind/x11/__init__.py
canaveral/qtkeybind/x11/keybindutil.py
canaveral/qtkeybind/x11/keysymdef.py
canaveral/qtkeybind/x11/qt_keycodes.py
canaveral/resources/light_background.png
canaveral/resources/light_background_2x.png
canaveral/resources/rocket_with_shadow.ico
canaveral/resources/rocket_with_shadow.png
canaveral/resources/rocket_with_shadow_blue.ico
canaveral/resources/rocket_with_shadow_blue.png
canaveral/resources/rocket_with_shadow_blue_256px.png
canaveral/resources/search_icon.png
canaveral-0.1.0.dist-info/LICENSE
canaveral-0.1.0.dist-info/METADATA
canaveral-0.1.0.dist-info/WHEEL
canaveral-0.1.0.dist-info/entry_points.txt
canaveral-0.1.0.dist-info/top_level.txt
canaveral-0.1.0.dist-info/RECORD
