Metadata-Version: 2.1
Name: canaveral
Version: 0.1.0
Summary: Quickly find and open applications and files
Home-page: https://github.com/joshburnett/canaveral
Author: Josh Burnett
Author-email: github@burnettsonline.org
License: MIT
Keywords: canaveral launcher launch utility keyboard
Platform: windows
Classifier: Development Status :: 3 - Alpha
Classifier: Intended Audience :: End Users/Desktop
Classifier: Environment :: Win32 (MS Windows)
Classifier: License :: OSI Approved :: MIT License
Classifier: Programming Language :: Python
Classifier: Programming Language :: Python :: 3
Classifier: Programming Language :: Python :: 3.8
Classifier: Programming Language :: Python :: 3.9
Classifier: Topic :: Utilities
Requires-Dist: pyside6
Requires-Dist: pywin32
Requires-Dist: loguru
Requires-Dist: stringscore
Requires-Dist: winpath
Requires-Dist: PyYAML
Requires-Dist: prettyprinter
Requires-Dist: appdirs
Requires-Dist: tabulate
Requires-Dist: numpy
